smat/__init__.py
smat/api.py
smat/api_logging.py
smat/sites.py
smat/utils.py
smat-0.2.0.dist-info/LICENSE
smat-0.2.0.dist-info/METADATA
smat-0.2.0.dist-info/WHEEL
smat-0.2.0.dist-info/top_level.txt
smat-0.2.0.dist-info/RECORD
